bmdal_reg
