Metadata-Version: 2.1
Name: bmdal-reg
Version: 3.0.1
Summary: Deep Batch Active Learning for Regression
Home-page: https://github.com/dholzmueller/bmdal_reg
Author: David Holzmüller
Author-email: nextuser@live.de
License: Apache 2.0
Platform: UNKNOWN
Classifier: Development Status :: 4 - Beta
Classifier: Intended Audience :: Science/Research
Classifier: License :: OSI Approved :: Apache Software License
Classifier: Operating System :: POSIX :: Linux
Classifier: Programming Language :: Python :: 3
License-File: LICENSE
License-File: NOTICE
